[
    {
        "timestamp": "2025-07-13T03:25:00.267385",
        "symbol": "AST/USDT",
        "sell_exchange": "Gate.io",
        "sell_price": 0.041425000000000003,
        "buy_exchange": "MEXC",
        "buy_price": 0.0069949999999999995,
        "diff_percent": 492.2087205146534
    },
    {
        "timestamp": "2025-07-13T03:25:00.267385",
        "symbol": "XRP3S/USDT",
        "sell_exchange": "KuCoin",
        "sell_price": 0.014752999999999999,
        "buy_exchange": "Gate.io",
        "buy_price": 0.002497,
        "diff_percent": 490.8289947937525
    },
    {
        "timestamp": "2025-07-13T03:25:00.267385",
        "symbol": "BEAM/USDT",
        "sell_exchange": "MEXC",
        "sell_price": 0.035675,
        "buy_exchange": "Bybit",
        "buy_price": 0.006647999999999999,
        "diff_percent": 436.6275571600481
    },
    {
        "timestamp": "2025-07-13T03:25:00.267385",
        "symbol": "NAWS/USDT",
        "sell_exchange": "Gate.io",
        "sell_price": 0.001071405,
        "buy_exchange": "MEXC",
        "buy_price": 0.000218305,
        "diff_percent": 390.7835367948513
    },
    {
        "timestamp": "2025-07-13T03:25:00.267385",
        "symbol": "PTC/USDT",
        "sell_exchange": "Gate.io",
        "sell_price": 0.0060704999999999995,
        "buy_exchange": "MEXC",
        "buy_price": 0.0013020000000000002,
        "diff_percent": 366.2442396313363
    },
    {
        "timestamp": "2025-07-13T03:25:00.267385",
        "symbol": "ETH3L/USDT",
        "sell_exchange": "KuCoin",
        "sell_price": 5.4775,
        "buy_exchange": "Gate.io",
        "buy_price": 1.34015,
        "diff_percent": 308.72290415252024
    },
    {
        "timestamp": "2025-07-13T03:25:00.267385",
        "symbol": "DOAI/USDT",
        "sell_exchange": "KuCoin",
        "sell_price": 0.00099605,
        "buy_exchange": "Gate.io",
        "buy_price": 0.0002508,
        "diff_percent": 297.14912280701753
    },
    {
        "timestamp": "2025-07-13T03:25:00.267385",
        "symbol": "QI/USDT",
        "sell_exchange": "Binance",
        "sell_price": 0.006705,
        "buy_exchange": "MEXC",
        "buy_price": 0.001892,
        "diff_percent": 254.3868921775898
    },
    {
        "timestamp": "2025-07-13T03:25:00.267385",
        "symbol": "ELIZA/USDT",
        "sell_exchange": "HTX",
        "sell_price": 0.00203,
        "buy_exchange": "Gate.io",
        "buy_price": 0.00059815,
        "diff_percent": 239.37975424224697
    },
    {
        "timestamp": "2025-07-13T03:25:00.267385",
        "symbol": "RAI/USDT",
        "sell_exchange": "Gate.io",
        "sell_price": 2.5445,
        "buy_exchange": "MEXC",
        "buy_price": 0.8444,
        "diff_percent": 201.33822832780672
    },
    {
        "timestamp": "2025-07-13T03:25:00.267385",
        "symbol": "LAI/USDT",
        "sell_exchange": "KuCoin",
        "sell_price": 0.00138,
        "buy_exchange": "Gate.io",
        "buy_price": 0.00045975,
        "diff_percent": 200.163132137031
    },
    {
        "timestamp": "2025-07-13T03:25:00.267385",
        "symbol": "GMRT/USDT",
        "sell_exchange": "Gate.io",
        "sell_price": 0.015585,
        "buy_exchange": "MEXC",
        "buy_price": 0.005485,
        "diff_percent": 184.13855970829533
    },
    {
        "timestamp": "2025-07-13T03:25:00.267385",
        "symbol": "OMNIA/USDT",
        "sell_exchange": "HTX",
        "sell_price": 0.028249999999999997,
        "buy_exchange": "MEXC",
        "buy_price": 0.010714999999999999,
        "diff_percent": 163.64909006066262
    },
    {
        "timestamp": "2025-07-13T03:25:00.267385",
        "symbol": "IRON/USDT",
        "sell_exchange": "KuCoin",
        "sell_price": 0.4095,
        "buy_exchange": "MEXC",
        "buy_price": 0.15585,
        "diff_percent": 162.75264677574592
    },
    {
        "timestamp": "2025-07-13T03:25:00.267385",
        "symbol": "TRIAS/USDT",
        "sell_exchange": "KuCoin",
        "sell_price": 2.3775000000000004,
        "buy_exchange": "Gate.io",
        "buy_price": 0.99045,
        "diff_percent": 140.04240496743907
    },
    {
        "timestamp": "2025-07-13T03:25:00.267385",
        "symbol": "GST/USDT",
        "sell_exchange": "MEXC",
        "sell_price": 0.0064410000000000005,
        "buy_exchange": "Gate.io",
        "buy_price": 0.0027489999999999997,
        "diff_percent": 134.30338304838128
    },
    {
        "timestamp": "2025-07-13T03:25:00.267385",
        "symbol": "UWON/USDT",
        "sell_exchange": "WhiteBIT",
        "sell_price": 0.7162,
        "buy_exchange": "MEXC",
        "buy_price": 0.31255,
        "diff_percent": 129.1473364261718
    },
    {
        "timestamp": "2025-07-13T03:25:00.267385",
        "symbol": "OPEN/USDT",
        "sell_exchange": "KuCoin",
        "sell_price": 0.0037045,
        "buy_exchange": "MEXC",
        "buy_price": 0.00164145,
        "diff_percent": 125.68460812086872
    },
    {
        "timestamp": "2025-07-13T03:25:00.267385",
        "symbol": "CAW/USDT",
        "sell_exchange": "MEXC",
        "sell_price": 4.5551499999999996e-08,
        "buy_exchange": "Gate.io",
        "buy_price": 2.0989999999999998e-08,
        "diff_percent": 117.01524535493093
    },
    {
        "timestamp": "2025-07-13T03:25:00.267385",
        "symbol": "RWA/USDT",
        "sell_exchange": "KuCoin",
        "sell_price": 0.008684,
        "buy_exchange": "MEXC",
        "buy_price": 0.0040245,
        "diff_percent": 115.77835755994535
    },
    {
        "timestamp": "2025-07-13T03:25:00.267385",
        "symbol": "URO/USDT",
        "sell_exchange": "MEXC",
        "sell_price": 0.0018725,
        "buy_exchange": "Gate.io",
        "buy_price": 0.0009330499999999999,
        "diff_percent": 100.68592251219121
    },
    {
        "timestamp": "2025-07-13T03:25:00.267385",
        "symbol": "GOATS/USDT",
        "sell_exchange": "Gate.io",
        "sell_price": 0.0001314,
        "buy_exchange": "MEXC",
        "buy_price": 6.7065e-05,
        "diff_percent": 95.92932229926193
    },
    {
        "timestamp": "2025-07-13T03:25:00.267385",
        "symbol": "ERN/USDT",
        "sell_exchange": "KuCoin",
        "sell_price": 1.7861500000000001,
        "buy_exchange": "OKX",
        "buy_price": 0.9485,
        "diff_percent": 88.31312598840275
    },
    {
        "timestamp": "2025-07-13T03:25:00.267385",
        "symbol": "KAI/USDT",
        "sell_exchange": "KuCoin",
        "sell_price": 0.0016575499999999998,
        "buy_exchange": "Gate.io",
        "buy_price": 0.0009713,
        "diff_percent": 70.65273345001542
    },
    {
        "timestamp": "2025-07-13T03:25:00.267385",
        "symbol": "SCRT/USDT",
        "sell_exchange": "HTX",
        "sell_price": 0.2843,
        "buy_exchange": "KuCoin",
        "buy_price": 0.17665,
        "diff_percent": 60.93971129351825
    },
    {
        "timestamp": "2025-07-13T03:25:00.267385",
        "symbol": "MLN/USDT",
        "sell_exchange": "HTX",
        "sell_price": 12.1745,
        "buy_exchange": "OKX",
        "buy_price": 7.729,
        "diff_percent": 57.51714322680812
    },
    {
        "timestamp": "2025-07-13T03:25:00.267385",
        "symbol": "REEF/USDT",
        "sell_exchange": "HTX",
        "sell_price": 0.00033850000000000004,
        "buy_exchange": "Gate.io",
        "buy_price": 0.00021525,
        "diff_percent": 57.2590011614402
    },
    {
        "timestamp": "2025-07-13T03:25:00.267385",
        "symbol": "TUNE/USDT",
        "sell_exchange": "KuCoin",
        "sell_price": 0.004255,
        "buy_exchange": "Gate.io",
        "buy_price": 0.0028763499999999997,
        "diff_percent": 47.930536965251115
    },
    {
        "timestamp": "2025-07-13T03:25:00.267385",
        "symbol": "XTM/USDT",
        "sell_exchange": "KuCoin",
        "sell_price": 0.009121,
        "buy_exchange": "MEXC",
        "buy_price": 0.00618,
        "diff_percent": 47.58899676375406
    },
    {
        "timestamp": "2025-07-13T03:25:00.267385",
        "symbol": "SNS/USDT",
        "sell_exchange": "HTX",
        "sell_price": 0.002304,
        "buy_exchange": "Gate.io",
        "buy_price": 0.0015845,
        "diff_percent": 45.40864626065005
    },
    {
        "timestamp": "2025-07-13T03:25:00.267385",
        "symbol": "EOS/USDT",
        "sell_exchange": "KuCoin",
        "sell_price": 0.76225,
        "buy_exchange": "Kraken",
        "buy_price": 0.52715,
        "diff_percent": 44.59831167599354
    },
    {
        "timestamp": "2025-07-13T03:25:00.267385",
        "symbol": "ZK/USDT",
        "sell_exchange": "HTX",
        "sell_price": 0.07575,
        "buy_exchange": "Gate.io",
        "buy_price": 0.05381,
        "diff_percent": 40.77309050362386
    },
    {
        "timestamp": "2025-07-13T03:25:00.267385",
        "symbol": "POLC/USDT",
        "sell_exchange": "MEXC",
        "sell_price": 0.002988,
        "buy_exchange": "Gate.io",
        "buy_price": 0.0022589999999999997,
        "diff_percent": 32.27091633466138
    },
    {
        "timestamp": "2025-07-13T03:25:00.267385",
        "symbol": "DGB/USDT",
        "sell_exchange": "HTX",
        "sell_price": 0.0110895,
        "buy_exchange": "OKX",
        "buy_price": 0.008489,
        "diff_percent": 30.633761338202387
    },
    {
        "timestamp": "2025-07-13T03:25:00.267385",
        "symbol": "CLV/USDT",
        "sell_exchange": "MEXC",
        "sell_price": 0.022,
        "buy_exchange": "Gate.io",
        "buy_price": 0.016885,
        "diff_percent": 30.293159609120508
    },
    {
        "timestamp": "2025-07-13T03:25:00.267385",
        "symbol": "DEFI/USDT",
        "sell_exchange": "Gate.io",
        "sell_price": 0.002763,
        "buy_exchange": "MEXC",
        "buy_price": 0.0021904999999999997,
        "diff_percent": 26.135585482766498
    },
    {
        "timestamp": "2025-07-13T03:25:00.267385",
        "symbol": "MAN/USDT",
        "sell_exchange": "MEXC",
        "sell_price": 0.007509999999999999,
        "buy_exchange": "Gate.io",
        "buy_price": 0.006196500000000001,
        "diff_percent": 21.19745017348501
    },
    {
        "timestamp": "2025-07-13T03:25:00.267385",
        "symbol": "GET/USDT",
        "sell_exchange": "Gate.io",
        "sell_price": 0.0109305,
        "buy_exchange": "MEXC",
        "buy_price": 0.009193,
        "diff_percent": 18.90025019036223
    },
    {
        "timestamp": "2025-07-13T03:25:00.267385",
        "symbol": "VELAAI/USDT",
        "sell_exchange": "Gate.io",
        "sell_price": 0.013535,
        "buy_exchange": "MEXC",
        "buy_price": 0.01156,
        "diff_percent": 17.084775086505182
    },
    {
        "timestamp": "2025-07-13T03:25:00.267385",
        "symbol": "IDEA/USDT",
        "sell_exchange": "KuCoin",
        "sell_price": 9.3e-05,
        "buy_exchange": "Gate.io",
        "buy_price": 8.223e-05,
        "diff_percent": 13.097409704487406
    },
    {
        "timestamp": "2025-07-13T03:25:00.267385",
        "symbol": "POND/USDT",
        "sell_exchange": "HTX",
        "sell_price": 0.009862,
        "buy_exchange": "Gate.io",
        "buy_price": 0.0087285,
        "diff_percent": 12.986194649710708
    },
    {
        "timestamp": "2025-07-13T03:25:00.267385",
        "symbol": "DOGE3L/USDT",
        "sell_exchange": "KuCoin",
        "sell_price": 0.039085999999999996,
        "buy_exchange": "Gate.io",
        "buy_price": 0.034699999999999995,
        "diff_percent": 12.639769452449572
    },
    {
        "timestamp": "2025-07-13T03:25:00.267385",
        "symbol": "WSDM/USDT",
        "sell_exchange": "KuCoin",
        "sell_price": 0.0016835,
        "buy_exchange": "Gate.io",
        "buy_price": 0.0015140000000000002,
        "diff_percent": 11.195508586525754
    },
    {
        "timestamp": "2025-07-13T03:25:00.267385",
        "symbol": "ASS/USDT",
        "sell_exchange": "MEXC",
        "sell_price": 8.867e-10,
        "buy_exchange": "Gate.io",
        "buy_price": 8.0495e-10,
        "diff_percent": 10.155910304987895
    },
    {
        "timestamp": "2025-07-13T03:25:00.267385",
        "symbol": "PIT/USDT",
        "sell_exchange": "MEXC",
        "sell_price": 2.5185e-10,
        "buy_exchange": "Gate.io",
        "buy_price": 2.34e-10,
        "diff_percent": 7.628205128205126
    },
    {
        "timestamp": "2025-07-13T03:25:00.267385",
        "symbol": "XRP3L/USDT",
        "sell_exchange": "Gate.io",
        "sell_price": 5.698,
        "buy_exchange": "KuCoin",
        "buy_price": 5.30705,
        "diff_percent": 7.366616104992419
    },
    {
        "timestamp": "2025-07-13T03:25:00.267385",
        "symbol": "OPTIMUS/USDT",
        "sell_exchange": "Gate.io",
        "sell_price": 0.022345,
        "buy_exchange": "MEXC",
        "buy_price": 0.020935000000000002,
        "diff_percent": 6.735132553140663
    },
    {
        "timestamp": "2025-07-13T03:25:00.267385",
        "symbol": "TRAC/USDT",
        "sell_exchange": "Gate.io",
        "sell_price": 0.3484,
        "buy_exchange": "HTX",
        "buy_price": 0.3273,
        "diff_percent": 6.446684998472351
    },
    {
        "timestamp": "2025-07-13T03:25:00.267385",
        "symbol": "KLV/USDT",
        "sell_exchange": "HTX",
        "sell_price": 0.002112,
        "buy_exchange": "Gate.io",
        "buy_price": 0.001985,
        "diff_percent": 6.397984886649893
    },
    {
        "timestamp": "2025-07-13T03:25:00.267385",
        "symbol": "MGT/USDT",
        "sell_exchange": "Gate.io",
        "sell_price": 0.00053365,
        "buy_exchange": "KuCoin",
        "buy_price": 0.0005059999999999999,
        "diff_percent": 5.464426877470366
    },
    {
        "timestamp": "2025-07-13T03:25:00.267385",
        "symbol": "TSUGT/USDT",
        "sell_exchange": "Gate.io",
        "sell_price": 0.0007449,
        "buy_exchange": "MEXC",
        "buy_price": 0.0007124,
        "diff_percent": 4.562043795620435
    },
    {
        "timestamp": "2025-07-13T03:25:00.267385",
        "symbol": "THN/USDT",
        "sell_exchange": "Gate.io",
        "sell_price": 0.0005708,
        "buy_exchange": "Bybit",
        "buy_price": 0.000546,
        "diff_percent": 4.542124542124533
    },
    {
        "timestamp": "2025-07-13T03:25:00.267385",
        "symbol": "SRM/USDT",
        "sell_exchange": "Gate.io",
        "sell_price": 0.01431,
        "buy_exchange": "MEXC",
        "buy_price": 0.013745,
        "diff_percent": 4.110585667515457
    },
    {
        "timestamp": "2025-07-13T03:25:00.267385",
        "symbol": "WHITE/USDT",
        "sell_exchange": "MEXC",
        "sell_price": 0.00043065,
        "buy_exchange": "Gate.io",
        "buy_price": 0.0004138,
        "diff_percent": 4.072015466408894
    },
    {
        "timestamp": "2025-07-13T03:25:00.267385",
        "symbol": "AIOT/USDT",
        "sell_exchange": "CoinEx",
        "sell_price": 0.206914,
        "buy_exchange": "MEXC",
        "buy_price": 0.198935,
        "diff_percent": 4.010857817880205
    },
    {
        "timestamp": "2025-07-13T03:25:00.267385",
        "symbol": "IGT/USDT",
        "sell_exchange": "Gate.io",
        "sell_price": 0.21705,
        "buy_exchange": "MEXC",
        "buy_price": 0.2087,
        "diff_percent": 4.00095831336847
    },
    {
        "timestamp": "2025-07-13T03:25:00.267385",
        "symbol": "GX/USDT",
        "sell_exchange": "MEXC",
        "sell_price": 0.00065415,
        "buy_exchange": "KuCoin",
        "buy_price": 0.000629,
        "diff_percent": 3.9984101748807697
    },
    {
        "timestamp": "2025-07-13T03:25:00.267385",
        "symbol": "E4C/USDT",
        "sell_exchange": "KuCoin",
        "sell_price": 0.0038850000000000004,
        "buy_exchange": "Gate.io",
        "buy_price": 0.003742,
        "diff_percent": 3.8214858364511044
    },
    {
        "timestamp": "2025-07-13T03:25:00.267385",
        "symbol": "B3TR/USDT",
        "sell_exchange": "Bybit",
        "sell_price": 0.068805,
        "buy_exchange": "MEXC",
        "buy_price": 0.06645000000000001,
        "diff_percent": 3.5440180586907384
    },
    {
        "timestamp": "2025-07-13T03:25:00.267385",
        "symbol": "PIG/USDT",
        "sell_exchange": "MEXC",
        "sell_price": 1.7485e-08,
        "buy_exchange": "Gate.io",
        "buy_price": 1.689e-08,
        "diff_percent": 3.522794552989933
    },
    {
        "timestamp": "2025-07-13T03:25:00.267385",
        "symbol": "INSP/USDT",
        "sell_exchange": "Bybit",
        "sell_price": 0.019929000000000002,
        "buy_exchange": "CoinEx",
        "buy_price": 0.019252,
        "diff_percent": 3.5165177643881362
    },
    {
        "timestamp": "2025-07-13T03:25:00.267385",
        "symbol": "SUT/USDT",
        "sell_exchange": "Gate.io",
        "sell_price": 5.452500000000001,
        "buy_exchange": "MEXC",
        "buy_price": 5.2705,
        "diff_percent": 3.4531828099800848
    },
    {
        "timestamp": "2025-07-13T03:25:00.267385",
        "symbol": "VPR/USDT",
        "sell_exchange": "MEXC",
        "sell_price": 0.0006345000000000001,
        "buy_exchange": "Bybit",
        "buy_price": 0.0006134000000000001,
        "diff_percent": 3.4398434952722567
    },
    {
        "timestamp": "2025-07-13T03:25:00.267385",
        "symbol": "BBQ/USDT",
        "sell_exchange": "Gate.io",
        "sell_price": 0.0112825,
        "buy_exchange": "Bybit",
        "buy_price": 0.010915,
        "diff_percent": 3.3669262482821947
    },
    {
        "timestamp": "2025-07-13T03:25:00.267385",
        "symbol": "XETA/USDT",
        "sell_exchange": "HTX",
        "sell_price": 0.0003075,
        "buy_exchange": "Bybit",
        "buy_price": 0.0002975,
        "diff_percent": 3.3613445378151163
    },
    {
        "timestamp": "2025-07-13T03:25:00.267385",
        "symbol": "MOJO/USDT",
        "sell_exchange": "Bybit",
        "sell_price": 0.001258,
        "buy_exchange": "Gate.io",
        "buy_price": 0.00121735,
        "diff_percent": 3.339220437836278
    },
    {
        "timestamp": "2025-07-13T03:25:00.267385",
        "symbol": "SWAN/USDT",
        "sell_exchange": "MEXC",
        "sell_price": 0.004031,
        "buy_exchange": "Gate.io",
        "buy_price": 0.003901,
        "diff_percent": 3.332478851576517
    },
    {
        "timestamp": "2025-07-13T03:25:00.267385",
        "symbol": "WNXM/USDT",
        "sell_exchange": "Gate.io",
        "sell_price": 66.425,
        "buy_exchange": "MEXC",
        "buy_price": 64.33500000000001,
        "diff_percent": 3.2486205020595147
    },
    {
        "timestamp": "2025-07-13T03:25:00.267385",
        "symbol": "ADS/USDT",
        "sell_exchange": "MEXC",
        "sell_price": 0.09426999999999999,
        "buy_exchange": "KuCoin",
        "buy_price": 0.09140000000000001,
        "diff_percent": 3.1400437636761307
    },
    {
        "timestamp": "2025-07-13T03:25:00.267385",
        "symbol": "KAON/USDT",
        "sell_exchange": "Gate.io",
        "sell_price": 0.00011605,
        "buy_exchange": "MEXC",
        "buy_price": 0.00011255,
        "diff_percent": 3.1097290093291905
    },
    {
        "timestamp": "2025-07-13T03:25:00.267385",
        "symbol": "BUZZ/USDT",
        "sell_exchange": "MEXC",
        "sell_price": 0.0082565,
        "buy_exchange": "Gate.io",
        "buy_price": 0.008036000000000001,
        "diff_percent": 2.743902439024371
    },
    {
        "timestamp": "2025-07-13T03:25:00.267385",
        "symbol": "COTI/USDT",
        "sell_exchange": "WhiteBIT",
        "sell_price": 0.05479,
        "buy_exchange": "KuCoin",
        "buy_price": 0.053349999999999995,
        "diff_percent": 2.699156513589511
    },
    {
        "timestamp": "2025-07-13T03:25:00.267385",
        "symbol": "KISHU/USDT",
        "sell_exchange": "MEXC",
        "sell_price": 8.652e-11,
        "buy_exchange": "Gate.io",
        "buy_price": 8.424999999999999e-11,
        "diff_percent": 2.6943620178041647
    },
    {
        "timestamp": "2025-07-13T03:25:00.267385",
        "symbol": "KT/USDT",
        "sell_exchange": "Gate.io",
        "sell_price": 0.00037985,
        "buy_exchange": "HTX",
        "buy_price": 0.00037,
        "diff_percent": 2.662162162162161
    },
    {
        "timestamp": "2025-07-13T03:25:00.267385",
        "symbol": "KCAL/USDT",
        "sell_exchange": "Gate.io",
        "sell_price": 0.0062775,
        "buy_exchange": "Bybit",
        "buy_price": 0.006118,
        "diff_percent": 2.6070611310885896
    },
    {
        "timestamp": "2025-07-13T03:25:00.267385",
        "symbol": "VRTX/USDT",
        "sell_exchange": "Gate.io",
        "sell_price": 0.001549,
        "buy_exchange": "Bybit",
        "buy_price": 0.00151,
        "diff_percent": 2.5827814569536405
    },
    {
        "timestamp": "2025-07-13T03:25:00.267385",
        "symbol": "KAR/USDT",
        "sell_exchange": "Gate.io",
        "sell_price": 0.02942,
        "buy_exchange": "MEXC",
        "buy_price": 0.02869,
        "diff_percent": 2.54444057162775
    },
    {
        "timestamp": "2025-07-13T03:25:00.267385",
        "symbol": "ASTRA/USDT",
        "sell_exchange": "MEXC",
        "sell_price": 0.0022615,
        "buy_exchange": "Gate.io",
        "buy_price": 0.0022065,
        "diff_percent": 2.4926353954226115
    },
    {
        "timestamp": "2025-07-13T03:25:00.267385",
        "symbol": "SLIM/USDT",
        "sell_exchange": "KuCoin",
        "sell_price": 0.05006,
        "buy_exchange": "MEXC",
        "buy_price": 0.048845,
        "diff_percent": 2.487460333708672
    },
    {
        "timestamp": "2025-07-13T03:25:00.267385",
        "symbol": "WLTH/USDT",
        "sell_exchange": "Gate.io",
        "sell_price": 0.0028770000000000002,
        "buy_exchange": "KuCoin",
        "buy_price": 0.0028075,
        "diff_percent": 2.475512021371331
    },
    {
        "timestamp": "2025-07-13T03:25:00.267385",
        "symbol": "VIVI/USDT",
        "sell_exchange": "Gate.io",
        "sell_price": 0.0194895,
        "buy_exchange": "MEXC",
        "buy_price": 0.0190195,
        "diff_percent": 2.4711480322826476
    },
    {
        "timestamp": "2025-07-13T03:25:00.267385",
        "symbol": "SYNT/USDT",
        "sell_exchange": "MEXC",
        "sell_price": 0.011415,
        "buy_exchange": "KuCoin",
        "buy_price": 0.011144999999999999,
        "diff_percent": 2.422611036339176
    },
    {
        "timestamp": "2025-07-13T03:25:00.267385",
        "symbol": "PACK/USDT",
        "sell_exchange": "MEXC",
        "sell_price": 0.022699999999999998,
        "buy_exchange": "Gate.io",
        "buy_price": 0.022170000000000002,
        "diff_percent": 2.3906179521876214
    },
    {
        "timestamp": "2025-07-13T03:25:00.267385",
        "symbol": "MSQ/USDT",
        "sell_exchange": "MEXC",
        "sell_price": 13.5885,
        "buy_exchange": "Gate.io",
        "buy_price": 13.2725,
        "diff_percent": 2.3808626860048894
    },
    {
        "timestamp": "2025-07-13T03:25:00.267385",
        "symbol": "MPC/USDT",
        "sell_exchange": "MEXC",
        "sell_price": 0.028925,
        "buy_exchange": "KuCoin",
        "buy_price": 0.028293,
        "diff_percent": 2.2337680698405986
    },
    {
        "timestamp": "2025-07-13T03:25:00.267385",
        "symbol": "KCT/USDT",
        "sell_exchange": "Gate.io",
        "sell_price": 0.00061855,
        "buy_exchange": "HTX",
        "buy_price": 0.00060505,
        "diff_percent": 2.231220560284284
    },
    {
        "timestamp": "2025-07-13T03:25:00.267385",
        "symbol": "SFI/USDT",
        "sell_exchange": "MEXC",
        "sell_price": 0.0348,
        "buy_exchange": "Gate.io",
        "buy_price": 0.03405,
        "diff_percent": 2.2026431718061694
    },
    {
        "timestamp": "2025-07-13T03:25:00.267385",
        "symbol": "VON/USDT",
        "sell_exchange": "MEXC",
        "sell_price": 2.3055999999999997e-05,
        "buy_exchange": "Gate.io",
        "buy_price": 2.2564999999999998e-05,
        "diff_percent": 2.1759361843563005
    },
    {
        "timestamp": "2025-07-13T03:25:00.267385",
        "symbol": "PORK/USDT",
        "sell_exchange": "MEXC",
        "sell_price": 5.6445e-08,
        "buy_exchange": "Gate.io",
        "buy_price": 5.5275e-08,
        "diff_percent": 2.1166892808683913
    },
    {
        "timestamp": "2025-07-13T03:25:00.267385",
        "symbol": "MUBI/USDT",
        "sell_exchange": "MEXC",
        "sell_price": 0.004217,
        "buy_exchange": "HTX",
        "buy_price": 0.00413,
        "diff_percent": 2.1065375302663503
    }
]