[
    {
        "timestamp": "2025-07-14T14:46:00.115922",
        "symbol": "ACP/USDT",
        "sell_exchange": "Gate.io",
        "sell_price": 0.0039109999999999995,
        "buy_exchange": "MEXC",
        "buy_price": 0.00010114999999999999,
        "diff_percent": 3766.534849233811
    },
    {
        "timestamp": "2025-07-14T14:46:00.115922",
        "symbol": "SUI3L/USDT",
        "sell_exchange": "Gate.io",
        "sell_price": 0.07837,
        "buy_exchange": "KuCoin",
        "buy_price": 0.0024289999999999997,
        "diff_percent": 3126.430629888843
    },
    {
        "timestamp": "2025-07-14T14:46:00.115922",
        "symbol": "ROCK/USDT",
        "sell_exchange": "Gate.io",
        "sell_price": 0.038505,
        "buy_exchange": "HTX",
        "buy_price": 0.00123288,
        "diff_percent": 3023.1750048666536
    },
    {
        "timestamp": "2025-07-14T14:46:00.115922",
        "symbol": "FIRE/USDT",
        "sell_exchange": "KuCoin",
        "sell_price": 0.013925,
        "buy_exchange": "Gate.io",
        "buy_price": 0.00046955,
        "diff_percent": 2865.605366840592
    },
    {
        "timestamp": "2025-07-14T14:46:00.115922",
        "symbol": "SOL3L/USDT",
        "sell_exchange": "Gate.io",
        "sell_price": 6.65,
        "buy_exchange": "KuCoin",
        "buy_price": 0.246732265,
        "diff_percent": 2595.2291788834345
    },
    {
        "timestamp": "2025-07-14T14:46:00.115922",
        "symbol": "RIF/USDT",
        "sell_exchange": "MEXC",
        "sell_price": 0.061869999999999994,
        "buy_exchange": "HTX",
        "buy_price": 0.002465,
        "diff_percent": 2409.939148073022
    },
    {
        "timestamp": "2025-07-14T14:46:00.115922",
        "symbol": "WOLF/USDT",
        "sell_exchange": "Gate.io",
        "sell_price": 5.3945e-05,
        "buy_exchange": "MEXC",
        "buy_price": 2.3480000000000002e-06,
        "diff_percent": 2197.487223168654
    },
    {
        "timestamp": "2025-07-14T14:46:00.115922",
        "symbol": "TST/USDT",
        "sell_exchange": "Binance",
        "sell_price": 0.042015,
        "buy_exchange": "Bybit",
        "buy_price": 0.002046,
        "diff_percent": 1953.5190615835772
    },
    {
        "timestamp": "2025-07-14T14:46:00.115922",
        "symbol": "ALT/USDT",
        "sell_exchange": "WhiteBIT",
        "sell_price": 0.03574,
        "buy_exchange": "MEXC",
        "buy_price": 0.0024045,
        "diff_percent": 1386.379704720316
    },
    {
        "timestamp": "2025-07-14T14:46:00.115922",
        "symbol": "AAVE3L/USDT",
        "sell_exchange": "Gate.io",
        "sell_price": 0.7012,
        "buy_exchange": "KuCoin",
        "buy_price": 0.07022584500000001,
        "diff_percent": 898.4927913647747
    },
    {
        "timestamp": "2025-07-14T14:46:00.115922",
        "symbol": "SON/USDT",
        "sell_exchange": "KuCoin",
        "sell_price": 0.0001496,
        "buy_exchange": "Bybit",
        "buy_price": 1.5815e-05,
        "diff_percent": 845.9374012013913
    },
    {
        "timestamp": "2025-07-14T14:46:00.115922",
        "symbol": "SUI3S/USDT",
        "sell_exchange": "Gate.io",
        "sell_price": 0.017070000000000002,
        "buy_exchange": "KuCoin",
        "buy_price": 0.00184,
        "diff_percent": 827.7173913043479
    },
    {
        "timestamp": "2025-07-14T14:46:00.115922",
        "symbol": "FMC/USDT",
        "sell_exchange": "MEXC",
        "sell_price": 0.0026996,
        "buy_exchange": "Bybit",
        "buy_price": 0.00029405,
        "diff_percent": 818.0751572861757
    },
    {
        "timestamp": "2025-07-14T14:46:00.115922",
        "symbol": "WXT/USDT",
        "sell_exchange": "MEXC",
        "sell_price": 0.0316975,
        "buy_exchange": "HTX",
        "buy_price": 0.0036049999999999997,
        "diff_percent": 779.2649098474342
    },
    {
        "timestamp": "2025-07-14T14:46:00.115922",
        "symbol": "HRT/USDT",
        "sell_exchange": "MEXC",
        "sell_price": 0.0005794999999999999,
        "buy_exchange": "Gate.io",
        "buy_price": 6.7365e-05,
        "diff_percent": 760.2389965115415
    },
    {
        "timestamp": "2025-07-14T14:46:00.115922",
        "symbol": "ORT/USDT",
        "sell_exchange": "MEXC",
        "sell_price": 0.004091,
        "buy_exchange": "Gate.io",
        "buy_price": 0.00048855,
        "diff_percent": 737.3759083000716
    },
    {
        "timestamp": "2025-07-14T14:46:00.115922",
        "symbol": "OPEN/USDT",
        "sell_exchange": "KuCoin",
        "sell_price": 0.0037045,
        "buy_exchange": "MEXC",
        "buy_price": 0.00045955,
        "diff_percent": 706.1146774018061
    },
    {
        "timestamp": "2025-07-14T14:46:00.115922",
        "symbol": "AST/USDT",
        "sell_exchange": "Gate.io",
        "sell_price": 0.04358,
        "buy_exchange": "MEXC",
        "buy_price": 0.006567,
        "diff_percent": 563.6211359829451
    },
    {
        "timestamp": "2025-07-14T14:46:00.115922",
        "symbol": "XRP3S/USDT",
        "sell_exchange": "KuCoin",
        "sell_price": 0.0110985,
        "buy_exchange": "Gate.io",
        "buy_price": 0.0018700000000000001,
        "diff_percent": 493.5026737967914
    },
    {
        "timestamp": "2025-07-14T14:46:00.115922",
        "symbol": "MORI/USDT",
        "sell_exchange": "KuCoin",
        "sell_price": 0.11865,
        "buy_exchange": "CoinEx",
        "buy_price": 0.0209675,
        "diff_percent": 465.87576010492427
    },
    {
        "timestamp": "2025-07-14T14:46:00.115922",
        "symbol": "PTC/USDT",
        "sell_exchange": "Gate.io",
        "sell_price": 0.0067115000000000005,
        "buy_exchange": "MEXC",
        "buy_price": 0.0013065,
        "diff_percent": 413.700727133563
    },
    {
        "timestamp": "2025-07-14T14:46:00.115922",
        "symbol": "BEAM/USDT",
        "sell_exchange": "MEXC",
        "sell_price": 0.034575,
        "buy_exchange": "WhiteBIT",
        "buy_price": 0.00698,
        "diff_percent": 395.3438395415473
    },
    {
        "timestamp": "2025-07-14T14:46:00.115922",
        "symbol": "ARC/USDT",
        "sell_exchange": "Gate.io",
        "sell_price": 0.03295,
        "buy_exchange": "MEXC",
        "buy_price": 0.00684,
        "diff_percent": 381.72514619883043
    },
    {
        "timestamp": "2025-07-14T14:46:00.115922",
        "symbol": "ETH3L/USDT",
        "sell_exchange": "KuCoin",
        "sell_price": 6.1004000000000005,
        "buy_exchange": "Gate.io",
        "buy_price": 1.4910999999999999,
        "diff_percent": 309.1207833143318
    },
    {
        "timestamp": "2025-07-14T14:46:00.115922",
        "symbol": "ELIZA/USDT",
        "sell_exchange": "HTX",
        "sell_price": 0.00211,
        "buy_exchange": "Gate.io",
        "buy_price": 0.00057705,
        "diff_percent": 265.65288969759985
    },
    {
        "timestamp": "2025-07-14T14:46:00.115922",
        "symbol": "QI/USDT",
        "sell_exchange": "Binance",
        "sell_price": 0.006954999999999999,
        "buy_exchange": "Gate.io",
        "buy_price": 0.0019076499999999999,
        "diff_percent": 264.5846984509737
    },
    {
        "timestamp": "2025-07-14T14:46:00.115922",
        "symbol": "NAWS/USDT",
        "sell_exchange": "Gate.io",
        "sell_price": 0.000833,
        "buy_exchange": "MEXC",
        "buy_price": 0.00023137,
        "diff_percent": 260.02939015429826
    },
    {
        "timestamp": "2025-07-14T14:46:00.115922",
        "symbol": "RAI/USDT",
        "sell_exchange": "Gate.io",
        "sell_price": 2.5445,
        "buy_exchange": "MEXC",
        "buy_price": 0.9316,
        "diff_percent": 173.13224559896955
    },
    {
        "timestamp": "2025-07-14T14:46:00.115922",
        "symbol": "DOAI/USDT",
        "sell_exchange": "KuCoin",
        "sell_price": 0.0007344000000000001,
        "buy_exchange": "Gate.io",
        "buy_price": 0.00026900000000000003,
        "diff_percent": 173.01115241635688
    },
    {
        "timestamp": "2025-07-14T14:46:00.115922",
        "symbol": "GMRT/USDT",
        "sell_exchange": "Gate.io",
        "sell_price": 0.015385,
        "buy_exchange": "MEXC",
        "buy_price": 0.005685,
        "diff_percent": 170.62445030782763
    },
    {
        "timestamp": "2025-07-14T14:46:00.115922",
        "symbol": "IRON/USDT",
        "sell_exchange": "KuCoin",
        "sell_price": 0.4095,
        "buy_exchange": "MEXC",
        "buy_price": 0.15685,
        "diff_percent": 161.07746254383167
    },
    {
        "timestamp": "2025-07-14T14:46:00.115922",
        "symbol": "TRIAS/USDT",
        "sell_exchange": "KuCoin",
        "sell_price": 2.3775000000000004,
        "buy_exchange": "MEXC",
        "buy_price": 0.97195,
        "diff_percent": 144.6113483203869
    },
    {
        "timestamp": "2025-07-14T14:46:00.115922",
        "symbol": "GST/USDT",
        "sell_exchange": "Bybit",
        "sell_price": 0.0066565,
        "buy_exchange": "Gate.io",
        "buy_price": 0.0027295,
        "diff_percent": 143.872504121634
    },
    {
        "timestamp": "2025-07-14T14:46:00.115922",
        "symbol": "RWA/USDT",
        "sell_exchange": "KuCoin",
        "sell_price": 0.008669,
        "buy_exchange": "Gate.io",
        "buy_price": 0.0040675,
        "diff_percent": 113.12845728334358
    },
    {
        "timestamp": "2025-07-14T14:46:00.115922",
        "symbol": "URO/USDT",
        "sell_exchange": "MEXC",
        "sell_price": 0.0020074999999999997,
        "buy_exchange": "Gate.io",
        "buy_price": 0.00094885,
        "diff_percent": 111.57190282974123
    },
    {
        "timestamp": "2025-07-14T14:46:00.115922",
        "symbol": "CAW/USDT",
        "sell_exchange": "MEXC",
        "sell_price": 4.7775e-08,
        "buy_exchange": "Gate.io",
        "buy_price": 2.3270000000000003e-08,
        "diff_percent": 105.30726256983239
    },
    {
        "timestamp": "2025-07-14T14:46:00.115922",
        "symbol": "GOATS/USDT",
        "sell_exchange": "Gate.io",
        "sell_price": 0.00013795,
        "buy_exchange": "MEXC",
        "buy_price": 6.852e-05,
        "diff_percent": 101.32807939287798
    },
    {
        "timestamp": "2025-07-14T14:46:00.115922",
        "symbol": "ERN/USDT",
        "sell_exchange": "KuCoin",
        "sell_price": 1.7861500000000001,
        "buy_exchange": "OKX",
        "buy_price": 0.97675,
        "diff_percent": 82.86664960327619
    },
    {
        "timestamp": "2025-07-14T14:46:00.115922",
        "symbol": "KAI/USDT",
        "sell_exchange": "KuCoin",
        "sell_price": 0.0016575499999999998,
        "buy_exchange": "Gate.io",
        "buy_price": 0.0009483499999999999,
        "diff_percent": 74.78251700321611
    },
    {
        "timestamp": "2025-07-14T14:46:00.115922",
        "symbol": "REEF/USDT",
        "sell_exchange": "HTX",
        "sell_price": 0.0003725,
        "buy_exchange": "Gate.io",
        "buy_price": 0.00022375,
        "diff_percent": 66.4804469273743
    },
    {
        "timestamp": "2025-07-14T14:46:00.115922",
        "symbol": "MLN/USDT",
        "sell_exchange": "HTX",
        "sell_price": 12.0606,
        "buy_exchange": "Binance",
        "buy_price": 7.965,
        "diff_percent": 51.41996233521658
    },
    {
        "timestamp": "2025-07-14T14:46:00.115922",
        "symbol": "DEFI/USDT",
        "sell_exchange": "Gate.io",
        "sell_price": 0.003474,
        "buy_exchange": "MEXC",
        "buy_price": 0.0023125000000000003,
        "diff_percent": 50.227027027027006
    },
    {
        "timestamp": "2025-07-14T14:46:00.115922",
        "symbol": "SCRT/USDT",
        "sell_exchange": "HTX",
        "sell_price": 0.2791,
        "buy_exchange": "Bybit",
        "buy_price": 0.18769999999999998,
        "diff_percent": 48.694725625998956
    },
    {
        "timestamp": "2025-07-14T14:46:00.115922",
        "symbol": "TUNE/USDT",
        "sell_exchange": "KuCoin",
        "sell_price": 0.004255,
        "buy_exchange": "Gate.io",
        "buy_price": 0.00287775,
        "diff_percent": 47.8585700634176
    },
    {
        "timestamp": "2025-07-14T14:46:00.115922",
        "symbol": "JAM/USDT",
        "sell_exchange": "Gate.io",
        "sell_price": 0.00011420000000000001,
        "buy_exchange": "MEXC",
        "buy_price": 7.805e-05,
        "diff_percent": 46.31646380525306
    },
    {
        "timestamp": "2025-07-14T14:46:00.115922",
        "symbol": "LAI/USDT",
        "sell_exchange": "MEXC",
        "sell_price": 0.00076545,
        "buy_exchange": "Gate.io",
        "buy_price": 0.0005421,
        "diff_percent": 41.20088544548976
    },
    {
        "timestamp": "2025-07-14T14:46:00.115922",
        "symbol": "VRTX/USDT",
        "sell_exchange": "Gate.io",
        "sell_price": 0.001807,
        "buy_exchange": "Bybit",
        "buy_price": 0.001315,
        "diff_percent": 37.41444866920152
    },
    {
        "timestamp": "2025-07-14T14:46:00.115922",
        "symbol": "SNS/USDT",
        "sell_exchange": "HTX",
        "sell_price": 0.002069,
        "buy_exchange": "Gate.io",
        "buy_price": 0.001513,
        "diff_percent": 36.74818241903503
    },
    {
        "timestamp": "2025-07-14T14:46:00.115922",
        "symbol": "CLV/USDT",
        "sell_exchange": "HTX",
        "sell_price": 0.0232,
        "buy_exchange": "Gate.io",
        "buy_price": 0.017230000000000002,
        "diff_percent": 34.648868253046984
    },
    {
        "timestamp": "2025-07-14T14:46:00.115922",
        "symbol": "POLC/USDT",
        "sell_exchange": "MEXC",
        "sell_price": 0.003065,
        "buy_exchange": "Gate.io",
        "buy_price": 0.00228,
        "diff_percent": 34.429824561403514
    },
    {
        "timestamp": "2025-07-14T14:46:00.115922",
        "symbol": "EOS/USDT",
        "sell_exchange": "KuCoin",
        "sell_price": 0.76225,
        "buy_exchange": "Kraken",
        "buy_price": 0.56765,
        "diff_percent": 34.28168765964943
    },
    {
        "timestamp": "2025-07-14T14:46:00.115922",
        "symbol": "ZK/USDT",
        "sell_exchange": "HTX",
        "sell_price": 0.0764,
        "buy_exchange": "KuCoin",
        "buy_price": 0.0576,
        "diff_percent": 32.638888888888886
    },
    {
        "timestamp": "2025-07-14T14:46:00.115922",
        "symbol": "DGB/USDT",
        "sell_exchange": "HTX",
        "sell_price": 0.0116495,
        "buy_exchange": "Binance",
        "buy_price": 0.008830000000000001,
        "diff_percent": 31.930917327293308
    },
    {
        "timestamp": "2025-07-14T14:46:00.115922",
        "symbol": "MAN/USDT",
        "sell_exchange": "MEXC",
        "sell_price": 0.008045,
        "buy_exchange": "Gate.io",
        "buy_price": 0.0062115,
        "diff_percent": 29.517829831763663
    },
    {
        "timestamp": "2025-07-14T14:46:00.115922",
        "symbol": "XTM/USDT",
        "sell_exchange": "CoinEx",
        "sell_price": 0.0076875,
        "buy_exchange": "MEXC",
        "buy_price": 0.006307500000000001,
        "diff_percent": 21.878715814506528
    },
    {
        "timestamp": "2025-07-14T14:46:00.115922",
        "symbol": "IGT/USDT",
        "sell_exchange": "Gate.io",
        "sell_price": 0.23225,
        "buy_exchange": "MEXC",
        "buy_price": 0.20405,
        "diff_percent": 13.820142122028914
    },
    {
        "timestamp": "2025-07-14T14:46:00.115922",
        "symbol": "VELAAI/USDT",
        "sell_exchange": "Gate.io",
        "sell_price": 0.012969999999999999,
        "buy_exchange": "MEXC",
        "buy_price": 0.011655,
        "diff_percent": 11.282711282711269
    },
    {
        "timestamp": "2025-07-14T14:46:00.115922",
        "symbol": "DOGE3L/USDT",
        "sell_exchange": "KuCoin",
        "sell_price": 0.0459505,
        "buy_exchange": "Gate.io",
        "buy_price": 0.041580000000000006,
        "diff_percent": 10.511063011062992
    },
    {
        "timestamp": "2025-07-14T14:46:00.115922",
        "symbol": "UDAO/USDT",
        "sell_exchange": "Gate.io",
        "sell_price": 0.12708999999999998,
        "buy_exchange": "MEXC",
        "buy_price": 0.1154,
        "diff_percent": 10.129982668977451
    },
    {
        "timestamp": "2025-07-14T14:46:00.115922",
        "symbol": "ASS/USDT",
        "sell_exchange": "MEXC",
        "sell_price": 8.675e-10,
        "buy_exchange": "Gate.io",
        "buy_price": 7.9715e-10,
        "diff_percent": 8.8251897384432
    },
    {
        "timestamp": "2025-07-14T14:46:00.115922",
        "symbol": "TRIBE/USDT",
        "sell_exchange": "MEXC",
        "sell_price": 0.4753,
        "buy_exchange": "Gate.io",
        "buy_price": 0.4383,
        "diff_percent": 8.441706593657306
    },
    {
        "timestamp": "2025-07-14T14:46:00.115922",
        "symbol": "XRP3L/USDT",
        "sell_exchange": "Gate.io",
        "sell_price": 7.236,
        "buy_exchange": "KuCoin",
        "buy_price": 6.67685,
        "diff_percent": 8.374458015381501
    },
    {
        "timestamp": "2025-07-14T14:46:00.115922",
        "symbol": "GX/USDT",
        "sell_exchange": "MEXC",
        "sell_price": 0.000608,
        "buy_exchange": "Gate.io",
        "buy_price": 0.00056295,
        "diff_percent": 8.0024868993694
    },
    {
        "timestamp": "2025-07-14T14:46:00.115922",
        "symbol": "NANO/USDT",
        "sell_exchange": "Gate.io",
        "sell_price": 0.93345,
        "buy_exchange": "HTX",
        "buy_price": 0.8694999999999999,
        "diff_percent": 7.3548016101207665
    },
    {
        "timestamp": "2025-07-14T14:46:00.115922",
        "symbol": "KLV/USDT",
        "sell_exchange": "HTX",
        "sell_price": 0.00213,
        "buy_exchange": "KuCoin",
        "buy_price": 0.0019845,
        "diff_percent": 7.331821617535892
    },
    {
        "timestamp": "2025-07-14T14:46:00.115922",
        "symbol": "XETA/USDT",
        "sell_exchange": "HTX",
        "sell_price": 0.0002715,
        "buy_exchange": "Bybit",
        "buy_price": 0.0002546,
        "diff_percent": 6.637863315003918
    },
    {
        "timestamp": "2025-07-14T14:46:00.115922",
        "symbol": "EQX/USDT",
        "sell_exchange": "Gate.io",
        "sell_price": 0.0011301,
        "buy_exchange": "KuCoin",
        "buy_price": 0.0010695000000000001,
        "diff_percent": 5.6661991584852585
    },
    {
        "timestamp": "2025-07-14T14:46:00.115922",
        "symbol": "SWAN/USDT",
        "sell_exchange": "Gate.io",
        "sell_price": 0.0093445,
        "buy_exchange": "MEXC",
        "buy_price": 0.0088595,
        "diff_percent": 5.474349568260072
    },
    {
        "timestamp": "2025-07-14T14:46:00.115922",
        "symbol": "KISHU/USDT",
        "sell_exchange": "MEXC",
        "sell_price": 9.348e-11,
        "buy_exchange": "Gate.io",
        "buy_price": 8.865e-11,
        "diff_percent": 5.448392554991537
    },
    {
        "timestamp": "2025-07-14T14:46:00.115922",
        "symbol": "TRAC/USDT",
        "sell_exchange": "Gate.io",
        "sell_price": 0.35935,
        "buy_exchange": "KuCoin",
        "buy_price": 0.34185,
        "diff_percent": 5.119204329384237
    },
    {
        "timestamp": "2025-07-14T14:46:00.115922",
        "symbol": "DFDVX/USDT",
        "sell_exchange": "MEXC",
        "sell_price": 27.424999999999997,
        "buy_exchange": "Gate.io",
        "buy_price": 26.09,
        "diff_percent": 5.116903027980059
    },
    {
        "timestamp": "2025-07-14T14:46:00.115922",
        "symbol": "PIG/USDT",
        "sell_exchange": "MEXC",
        "sell_price": 1.811e-08,
        "buy_exchange": "Gate.io",
        "buy_price": 1.726e-08,
        "diff_percent": 4.9246813441483255
    },
    {
        "timestamp": "2025-07-14T14:46:00.115922",
        "symbol": "ETHF/USDT",
        "sell_exchange": "HTX",
        "sell_price": 0.008739,
        "buy_exchange": "MEXC",
        "buy_price": 0.008347,
        "diff_percent": 4.696298071163292
    },
    {
        "timestamp": "2025-07-14T14:46:00.115922",
        "symbol": "BRAWL/USDT",
        "sell_exchange": "Gate.io",
        "sell_price": 1.506e-05,
        "buy_exchange": "KuCoin",
        "buy_price": 1.4449999999999999e-05,
        "diff_percent": 4.221453287197239
    },
    {
        "timestamp": "2025-07-14T14:46:00.115922",
        "symbol": "SC/USDT",
        "sell_exchange": "HTX",
        "sell_price": 0.003576,
        "buy_exchange": "Binance",
        "buy_price": 0.0034335,
        "diff_percent": 4.150283966797736
    },
    {
        "timestamp": "2025-07-14T14:46:00.115922",
        "symbol": "SHRUB/USDT",
        "sell_exchange": "Gate.io",
        "sell_price": 0.0043215,
        "buy_exchange": "MEXC",
        "buy_price": 0.0041615,
        "diff_percent": 3.844767511714515
    },
    {
        "timestamp": "2025-07-14T14:46:00.115922",
        "symbol": "CERE/USDT",
        "sell_exchange": "MEXC",
        "sell_price": 0.0015466999999999998,
        "buy_exchange": "Gate.io",
        "buy_price": 0.00149,
        "diff_percent": 3.8053691275167654
    },
    {
        "timestamp": "2025-07-14T14:46:00.115922",
        "symbol": "SYNT/USDT",
        "sell_exchange": "KuCoin",
        "sell_price": 0.012445000000000001,
        "buy_exchange": "MEXC",
        "buy_price": 0.012015,
        "diff_percent": 3.578859758635053
    },
    {
        "timestamp": "2025-07-14T14:46:00.115922",
        "symbol": "CREDI/USDT",
        "sell_exchange": "Gate.io",
        "sell_price": 0.0058285,
        "buy_exchange": "KuCoin",
        "buy_price": 0.0056415,
        "diff_percent": 3.314721262075699
    },
    {
        "timestamp": "2025-07-14T14:46:00.115922",
        "symbol": "NVIR/USDT",
        "sell_exchange": "MEXC",
        "sell_price": 0.0002745,
        "buy_exchange": "Gate.io",
        "buy_price": 0.0002659,
        "diff_percent": 3.234298608499433
    },
    {
        "timestamp": "2025-07-14T14:46:00.115922",
        "symbol": "MARSH/USDT",
        "sell_exchange": "Gate.io",
        "sell_price": 0.0183735,
        "buy_exchange": "MEXC",
        "buy_price": 0.017835499999999997,
        "diff_percent": 3.016455944604883
    },
    {
        "timestamp": "2025-07-14T14:46:00.115922",
        "symbol": "PYN/USDT",
        "sell_exchange": "Gate.io",
        "sell_price": 0.0021951,
        "buy_exchange": "MEXC",
        "buy_price": 0.0021314999999999997,
        "diff_percent": 2.983814215341331
    },
    {
        "timestamp": "2025-07-14T14:46:00.115922",
        "symbol": "4EVER/USDT",
        "sell_exchange": "Gate.io",
        "sell_price": 0.001296,
        "buy_exchange": "MEXC",
        "buy_price": 0.0012605,
        "diff_percent": 2.8163427211424166
    },
    {
        "timestamp": "2025-07-14T14:46:00.115922",
        "symbol": "HAT/USDT",
        "sell_exchange": "HTX",
        "sell_price": 0.000845,
        "buy_exchange": "Gate.io",
        "buy_price": 0.0008225,
        "diff_percent": 2.7355623100304025
    },
    {
        "timestamp": "2025-07-14T14:46:00.115922",
        "symbol": "SWAP/USDT",
        "sell_exchange": "HTX",
        "sell_price": 0.10605,
        "buy_exchange": "MEXC",
        "buy_price": 0.10324,
        "diff_percent": 2.7218132506780384
    },
    {
        "timestamp": "2025-07-14T14:46:00.115922",
        "symbol": "UBXS/USDT",
        "sell_exchange": "MEXC",
        "sell_price": 0.02476,
        "buy_exchange": "Gate.io",
        "buy_price": 0.024121999999999998,
        "diff_percent": 2.644888483542008
    },
    {
        "timestamp": "2025-07-14T14:46:00.115922",
        "symbol": "GMM/USDT",
        "sell_exchange": "MEXC",
        "sell_price": 4.7185e-05,
        "buy_exchange": "Gate.io",
        "buy_price": 4.6015e-05,
        "diff_percent": 2.542649136151264
    },
    {
        "timestamp": "2025-07-14T14:46:00.115922",
        "symbol": "KAR/USDT",
        "sell_exchange": "Gate.io",
        "sell_price": 0.03227,
        "buy_exchange": "MEXC",
        "buy_price": 0.03147,
        "diff_percent": 2.5421035907213287
    },
    {
        "timestamp": "2025-07-14T14:46:00.115922",
        "symbol": "NEUR/USDT",
        "sell_exchange": "MEXC",
        "sell_price": 0.0014045,
        "buy_exchange": "HTX",
        "buy_price": 0.0013700000000000001,
        "diff_percent": 2.5182481751824675
    },
    {
        "timestamp": "2025-07-14T14:46:00.115922",
        "symbol": "STOS/USDT",
        "sell_exchange": "MEXC",
        "sell_price": 0.1187,
        "buy_exchange": "Gate.io",
        "buy_price": 0.11585000000000001,
        "diff_percent": 2.460077686663782
    },
    {
        "timestamp": "2025-07-14T14:46:00.115922",
        "symbol": "ASTRA/USDT",
        "sell_exchange": "MEXC",
        "sell_price": 0.00251115,
        "buy_exchange": "Gate.io",
        "buy_price": 0.00245125,
        "diff_percent": 2.4436511983681926
    },
    {
        "timestamp": "2025-07-14T14:46:00.115922",
        "symbol": "CYBRO/USDT",
        "sell_exchange": "Gate.io",
        "sell_price": 0.005602,
        "buy_exchange": "MEXC",
        "buy_price": 0.00547,
        "diff_percent": 2.413162705667279
    },
    {
        "timestamp": "2025-07-14T14:46:00.115922",
        "symbol": "ITHACA/USDT",
        "sell_exchange": "Gate.io",
        "sell_price": 0.008916,
        "buy_exchange": "KuCoin",
        "buy_price": 0.008715,
        "diff_percent": 2.3063683304647133
    },
    {
        "timestamp": "2025-07-14T14:46:00.115922",
        "symbol": "OBT/USDT",
        "sell_exchange": "HTX",
        "sell_price": 0.0077350000000000006,
        "buy_exchange": "Gate.io",
        "buy_price": 0.0075645,
        "diff_percent": 2.253949368761987
    },
    {
        "timestamp": "2025-07-14T14:46:00.115922",
        "symbol": "AUCTION/USDT",
        "sell_exchange": "WhiteBIT",
        "sell_price": 12.2,
        "buy_exchange": "CoinEx",
        "buy_price": 11.9345,
        "diff_percent": 2.224642842180229
    },
    {
        "timestamp": "2025-07-14T14:46:00.115922",
        "symbol": "CHO/USDT",
        "sell_exchange": "MEXC",
        "sell_price": 0.004535,
        "buy_exchange": "Gate.io",
        "buy_price": 0.0044364999999999995,
        "diff_percent": 2.220218640820478
    },
    {
        "timestamp": "2025-07-14T14:46:00.115922",
        "symbol": "SUT/USDT",
        "sell_exchange": "Gate.io",
        "sell_price": 6.3535,
        "buy_exchange": "MEXC",
        "buy_price": 6.2175,
        "diff_percent": 2.187374346602334
    },
    {
        "timestamp": "2025-07-14T14:46:00.115922",
        "symbol": "ARCHAI/USDT",
        "sell_exchange": "Gate.io",
        "sell_price": 0.0030555,
        "buy_exchange": "MEXC",
        "buy_price": 0.0029915000000000002,
        "diff_percent": 2.139394952365028
    },
    {
        "timestamp": "2025-07-14T14:46:00.115922",
        "symbol": "S/USDT",
        "sell_exchange": "Kraken",
        "sell_price": 0.3764,
        "buy_exchange": "Binance",
        "buy_price": 0.36865000000000003,
        "diff_percent": 2.1022650210226446
    },
    {
        "timestamp": "2025-07-14T14:46:00.115922",
        "symbol": "LIKE/USDT",
        "sell_exchange": "Gate.io",
        "sell_price": 0.011589499999999999,
        "buy_exchange": "MEXC",
        "buy_price": 0.011353,
        "diff_percent": 2.083149828239222
    },
    {
        "timestamp": "2025-07-14T14:46:00.115922",
        "symbol": "AZUR/USDT",
        "sell_exchange": "Gate.io",
        "sell_price": 0.0066925,
        "buy_exchange": "MEXC",
        "buy_price": 0.0065575,
        "diff_percent": 2.058711399161261
    },
    {
        "timestamp": "2025-07-14T14:46:00.115922",
        "symbol": "MAGATRUMP/USDT",
        "sell_exchange": "Gate.io",
        "sell_price": 0.14434999999999998,
        "buy_exchange": "MEXC",
        "buy_price": 0.14145,
        "diff_percent": 2.0501944149876183
    },
    {
        "timestamp": "2025-07-14T14:46:00.115922",
        "symbol": "AARK/USDT",
        "sell_exchange": "Gate.io",
        "sell_price": 0.00117915,
        "buy_exchange": "Bybit",
        "buy_price": 0.0011554999999999998,
        "diff_percent": 2.0467330160103905
    },
    {
        "timestamp": "2025-07-14T14:46:00.115922",
        "symbol": "BOSON/USDT",
        "sell_exchange": "HTX",
        "sell_price": 0.10975,
        "buy_exchange": "KuCoin",
        "buy_price": 0.10755,
        "diff_percent": 2.0455602045560144
    },
    {
        "timestamp": "2025-07-14T14:46:00.115922",
        "symbol": "LOE/USDT",
        "sell_exchange": "Gate.io",
        "sell_price": 0.0028409999999999998,
        "buy_exchange": "MEXC",
        "buy_price": 0.002785,
        "diff_percent": 2.010771992818658
    }
]