[
    {
        "timestamp": "2025-07-12T20:52:00.139182",
        "symbol": "CERE/USDT",
        "sell_exchange": "MEXC",
        "sell_price": 0.0014266,
        "buy_exchange": "Gate.io",
        "buy_price": 0.001359,
        "diff_percent": 4.974245768947765
    },
    {
        "timestamp": "2025-07-12T20:52:00.139182",
        "symbol": "XETA/USDT",
        "sell_exchange": "HTX",
        "sell_price": 0.000306,
        "buy_exchange": "Gate.io",
        "buy_price": 0.0002921,
        "diff_percent": 4.7586442998973
    },
    {
        "timestamp": "2025-07-12T20:52:00.139182",
        "symbol": "MSQ/USDT",
        "sell_exchange": "MEXC",
        "sell_price": 13.917,
        "buy_exchange": "Gate.io",
        "buy_price": 13.294,
        "diff_percent": 4.686324657740329
    },
    {
        "timestamp": "2025-07-12T20:52:00.139182",
        "symbol": "GRAIL/USDT",
        "sell_exchange": "Gate.io",
        "sell_price": 361.15,
        "buy_exchange": "MEXC",
        "buy_price": 345.58500000000004,
        "diff_percent": 4.5039570583213795
    },
    {
        "timestamp": "2025-07-12T20:52:00.139182",
        "symbol": "WNXM/USDT",
        "sell_exchange": "Gate.io",
        "sell_price": 65.645,
        "buy_exchange": "MEXC",
        "buy_price": 63.04,
        "diff_percent": 4.132296954314716
    },
    {
        "timestamp": "2025-07-12T20:52:00.139182",
        "symbol": "BFTOKEN/USDT",
        "sell_exchange": "MEXC",
        "sell_price": 0.0059765,
        "buy_exchange": "Gate.io",
        "buy_price": 0.0057435,
        "diff_percent": 4.056759815443539
    },
    {
        "timestamp": "2025-07-12T20:52:00.139182",
        "symbol": "SAI/USDT",
        "sell_exchange": "Gate.io",
        "sell_price": 0.015955,
        "buy_exchange": "MEXC",
        "buy_price": 0.015335000000000001,
        "diff_percent": 4.0430388001304145
    },
    {
        "timestamp": "2025-07-12T20:52:00.139182",
        "symbol": "IGT/USDT",
        "sell_exchange": "Gate.io",
        "sell_price": 0.2197,
        "buy_exchange": "MEXC",
        "buy_price": 0.21135,
        "diff_percent": 3.9507925242488744
    },
    {
        "timestamp": "2025-07-12T20:52:00.139182",
        "symbol": "COTI/USDT",
        "sell_exchange": "WhiteBIT",
        "sell_price": 0.05608,
        "buy_exchange": "KuCoin",
        "buy_price": 0.05395,
        "diff_percent": 3.948100092678406
    },
    {
        "timestamp": "2025-07-12T20:52:00.139182",
        "symbol": "BOB/USDT",
        "sell_exchange": "KuCoin",
        "sell_price": 6.109e-06,
        "buy_exchange": "MEXC",
        "buy_price": 5.8795e-06,
        "diff_percent": 3.903393145675654
    },
    {
        "timestamp": "2025-07-12T20:52:00.139182",
        "symbol": "SYNT/USDT",
        "sell_exchange": "MEXC",
        "sell_price": 0.01158,
        "buy_exchange": "Gate.io",
        "buy_price": 0.011151,
        "diff_percent": 3.8471885929513103
    },
    {
        "timestamp": "2025-07-12T20:52:00.139182",
        "symbol": "ASS/USDT",
        "sell_exchange": "MEXC",
        "sell_price": 8.268500000000001e-10,
        "buy_exchange": "Gate.io",
        "buy_price": 7.9685e-10,
        "diff_percent": 3.764823994478271
    },
    {
        "timestamp": "2025-07-12T20:52:00.139182",
        "symbol": "SWAN/USDT",
        "sell_exchange": "MEXC",
        "sell_price": 0.00396,
        "buy_exchange": "Gate.io",
        "buy_price": 0.003817,
        "diff_percent": 3.7463976945244926
    },
    {
        "timestamp": "2025-07-12T20:52:00.139182",
        "symbol": "MARSH/USDT",
        "sell_exchange": "MEXC",
        "sell_price": 0.015516,
        "buy_exchange": "Gate.io",
        "buy_price": 0.014976,
        "diff_percent": 3.6057692307692344
    },
    {
        "timestamp": "2025-07-12T20:52:00.139182",
        "symbol": "MUBI/USDT",
        "sell_exchange": "KuCoin",
        "sell_price": 0.004209,
        "buy_exchange": "HTX",
        "buy_price": 0.00407,
        "diff_percent": 3.4152334152334216
    },
    {
        "timestamp": "2025-07-12T20:52:00.139182",
        "symbol": "MUNITY/USDT",
        "sell_exchange": "MEXC",
        "sell_price": 0.0007884999999999999,
        "buy_exchange": "Gate.io",
        "buy_price": 0.0007631000000000001,
        "diff_percent": 3.32852837111779
    },
    {
        "timestamp": "2025-07-12T20:52:00.139182",
        "symbol": "KCAL/USDT",
        "sell_exchange": "Bybit",
        "sell_price": 0.006099,
        "buy_exchange": "Gate.io",
        "buy_price": 0.005907000000000001,
        "diff_percent": 3.2503809040121796
    },
    {
        "timestamp": "2025-07-12T20:52:00.139182",
        "symbol": "FUSE/USDT",
        "sell_exchange": "MEXC",
        "sell_price": 0.0106695,
        "buy_exchange": "HTX",
        "buy_price": 0.010335,
        "diff_percent": 3.236574746008705
    },
    {
        "timestamp": "2025-07-12T20:52:00.139182",
        "symbol": "YULI/USDT",
        "sell_exchange": "Gate.io",
        "sell_price": 0.00034855,
        "buy_exchange": "KuCoin",
        "buy_price": 0.000339,
        "diff_percent": 2.817109144542769
    },
    {
        "timestamp": "2025-07-12T20:52:00.139182",
        "symbol": "ELYS/USDT",
        "sell_exchange": "MEXC",
        "sell_price": 0.0843,
        "buy_exchange": "Gate.io",
        "buy_price": 0.08204,
        "diff_percent": 2.7547537786445613
    },
    {
        "timestamp": "2025-07-12T20:52:00.139182",
        "symbol": "CTXC/USDT",
        "sell_exchange": "HTX",
        "sell_price": 0.07495,
        "buy_exchange": "MEXC",
        "buy_price": 0.072965,
        "diff_percent": 2.7204824230795595
    },
    {
        "timestamp": "2025-07-12T20:52:00.139182",
        "symbol": "TRIBE/USDT",
        "sell_exchange": "Gate.io",
        "sell_price": 0.4202,
        "buy_exchange": "MEXC",
        "buy_price": 0.40915,
        "diff_percent": 2.7007210069656615
    },
    {
        "timestamp": "2025-07-12T20:52:00.139182",
        "symbol": "AITECH/USDT",
        "sell_exchange": "WhiteBIT",
        "sell_price": 0.04268,
        "buy_exchange": "KuCoin",
        "buy_price": 0.04156,
        "diff_percent": 2.6948989412897086
    },
    {
        "timestamp": "2025-07-12T20:52:00.139182",
        "symbol": "PACK/USDT",
        "sell_exchange": "MEXC",
        "sell_price": 0.02346,
        "buy_exchange": "Gate.io",
        "buy_price": 0.022855,
        "diff_percent": 2.647123167796987
    },
    {
        "timestamp": "2025-07-12T20:52:00.139182",
        "symbol": "PIT/USDT",
        "sell_exchange": "MEXC",
        "sell_price": 2.502e-10,
        "buy_exchange": "Gate.io",
        "buy_price": 2.4385000000000004e-10,
        "diff_percent": 2.6040598728726603
    },
    {
        "timestamp": "2025-07-12T20:52:00.139182",
        "symbol": "ETHF/USDT",
        "sell_exchange": "MEXC",
        "sell_price": 0.008174,
        "buy_exchange": "HTX",
        "buy_price": 0.007969500000000001,
        "diff_percent": 2.5660330008156067
    },
    {
        "timestamp": "2025-07-12T20:52:00.139182",
        "symbol": "LUCE/USDT",
        "sell_exchange": "MEXC",
        "sell_price": 0.0046645,
        "buy_exchange": "Gate.io",
        "buy_price": 0.0045485000000000005,
        "diff_percent": 2.550291304825762
    },
    {
        "timestamp": "2025-07-12T20:52:00.139182",
        "symbol": "OLE/USDT",
        "sell_exchange": "MEXC",
        "sell_price": 0.006453,
        "buy_exchange": "Gate.io",
        "buy_price": 0.006293,
        "diff_percent": 2.54250754806929
    },
    {
        "timestamp": "2025-07-12T20:52:00.139182",
        "symbol": "ARDR/USDT",
        "sell_exchange": "HTX",
        "sell_price": 0.09465000000000001,
        "buy_exchange": "Binance",
        "buy_price": 0.09235,
        "diff_percent": 2.490525175961029
    },
    {
        "timestamp": "2025-07-12T20:52:00.139182",
        "symbol": "GXE/USDT",
        "sell_exchange": "MEXC",
        "sell_price": 0.002,
        "buy_exchange": "Gate.io",
        "buy_price": 0.0019515000000000001,
        "diff_percent": 2.485267742761974
    },
    {
        "timestamp": "2025-07-12T20:52:00.139182",
        "symbol": "DBC/USDT",
        "sell_exchange": "Gate.io",
        "sell_price": 0.00044300000000000003,
        "buy_exchange": "MEXC",
        "buy_price": 0.00043245,
        "diff_percent": 2.439588391721589
    },
    {
        "timestamp": "2025-07-12T20:52:00.139182",
        "symbol": "GPUAI/USDT",
        "sell_exchange": "MEXC",
        "sell_price": 0.46340000000000003,
        "buy_exchange": "Gate.io",
        "buy_price": 0.4526,
        "diff_percent": 2.3862129916040726
    },
    {
        "timestamp": "2025-07-12T20:52:00.139182",
        "symbol": "ASTRA/USDT",
        "sell_exchange": "Gate.io",
        "sell_price": 0.0019789,
        "buy_exchange": "MEXC",
        "buy_price": 0.0019342,
        "diff_percent": 2.3110329852135223
    },
    {
        "timestamp": "2025-07-12T20:52:00.139182",
        "symbol": "HDRO/USDT",
        "sell_exchange": "MEXC",
        "sell_price": 0.02549,
        "buy_exchange": "Gate.io",
        "buy_price": 0.024917,
        "diff_percent": 2.29963478749447
    },
    {
        "timestamp": "2025-07-12T20:52:00.139182",
        "symbol": "RBNT/USDT",
        "sell_exchange": "MEXC",
        "sell_price": 0.018514999999999997,
        "buy_exchange": "WhiteBIT",
        "buy_price": 0.0181,
        "diff_percent": 2.2928176795579844
    },
    {
        "timestamp": "2025-07-12T20:52:00.139182",
        "symbol": "BRN/USDT",
        "sell_exchange": "Gate.io",
        "sell_price": 0.14288499999999998,
        "buy_exchange": "MEXC",
        "buy_price": 0.1397,
        "diff_percent": 2.2798854688618424
    },
    {
        "timestamp": "2025-07-12T20:52:00.139182",
        "symbol": "KAON/USDT",
        "sell_exchange": "Gate.io",
        "sell_price": 0.0001139,
        "buy_exchange": "MEXC",
        "buy_price": 0.0001114,
        "diff_percent": 2.244165170556559
    },
    {
        "timestamp": "2025-07-12T20:52:00.139182",
        "symbol": "DOLO/USDT",
        "sell_exchange": "CoinEx",
        "sell_price": 0.05402,
        "buy_exchange": "MEXC",
        "buy_price": 0.052845,
        "diff_percent": 2.2234837732992627
    },
    {
        "timestamp": "2025-07-12T20:52:00.139182",
        "symbol": "DONKEY/USDT",
        "sell_exchange": "MEXC",
        "sell_price": 0.0014025,
        "buy_exchange": "HTX",
        "buy_price": 0.001372,
        "diff_percent": 2.223032069970856
    },
    {
        "timestamp": "2025-07-12T20:52:00.139182",
        "symbol": "DEAI/USDT",
        "sell_exchange": "Gate.io",
        "sell_price": 0.070555,
        "buy_exchange": "MEXC",
        "buy_price": 0.06903999999999999,
        "diff_percent": 2.194380069524937
    },
    {
        "timestamp": "2025-07-12T20:52:00.139182",
        "symbol": "BABYSHARK/USDT",
        "sell_exchange": "KuCoin",
        "sell_price": 0.0012165,
        "buy_exchange": "MEXC",
        "buy_price": 0.001191,
        "diff_percent": 2.141057934508809
    },
    {
        "timestamp": "2025-07-12T20:52:00.139182",
        "symbol": "LUNA/USDT",
        "sell_exchange": "HTX",
        "sell_price": 0.16970000000000002,
        "buy_exchange": "WhiteBIT",
        "buy_price": 0.1662,
        "diff_percent": 2.105896510228659
    },
    {
        "timestamp": "2025-07-12T20:52:00.139182",
        "symbol": "SAFFRONFI/USDT",
        "sell_exchange": "MEXC",
        "sell_price": 34.21,
        "buy_exchange": "Gate.io",
        "buy_price": 33.525,
        "diff_percent": 2.043251304996278
    },
    {
        "timestamp": "2025-07-12T20:52:00.139182",
        "symbol": "EVMOS/USDT",
        "sell_exchange": "Gate.io",
        "sell_price": 0.005190500000000001,
        "buy_exchange": "MEXC",
        "buy_price": 0.0050885,
        "diff_percent": 2.004519996069579
    }
]